first_project/__init__.py
rusu_first_project-0.1.0.dist-info/METADATA
rusu_first_project-0.1.0.dist-info/WHEEL
rusu_first_project-0.1.0.dist-info/top_level.txt
rusu_first_project-0.1.0.dist-info/RECORD
