Metadata-Version: 2.1
Name: rusu-first-project
Version: 0.1.0
Summary: says hello from Rusu
Author: Geokox
Author-email: rusugeorgevlad@gmail.com
License: UNKNOWN
Platform: UNKNOWN
Requires-Dist: dinosay
